valiot_worker/__init__.py
valiot_worker/client.py
valiot_worker/queries.py
valiot_worker/text.py
valiot_worker/worker.py
valiot_worker-1.0.dist-info/LICENSE
valiot_worker-1.0.dist-info/METADATA
valiot_worker-1.0.dist-info/WHEEL
valiot_worker-1.0.dist-info/top_level.txt
valiot_worker-1.0.dist-info/RECORD
