Metadata-Version: 2.1
Name: valiot-worker
Version: 1.0
Summary: The best worker ever.
Home-page: http://github.com/valiot/valiot_worker
Author: Mich B
Author-email: michel@valiot.io
License: MIT
Platform: UNKNOWN
Requires-Dist: valiot-worker
Requires-Dist: python-dotenv
Requires-Dist: requests
Requires-Dist: colorama
Requires-Dist: termcolor
